notifypy/__init__.py
notifypy/cli.py
notifypy/example_notification_sound.wav
notifypy/exceptions.py
notifypy/notify.py
notifypy/os_notifiers/__init__.py
notifypy/os_notifiers/_base.py
notifypy/os_notifiers/binaries/Notificator.app/Contents/Info.plist
notifypy/os_notifiers/binaries/Notificator.app/Contents/MacOS/applet
notifypy/os_notifiers/binaries/Notificator.app/Contents/PkgInfo
notifypy/os_notifiers/binaries/Notificator.app/Contents/Resources/Scripts/main.scpt
notifypy/os_notifiers/binaries/Notificator.app/Contents/Resources/Scripts/notificator
notifypy/os_notifiers/binaries/Notificator.app/Contents/Resources/applet.icns
notifypy/os_notifiers/binaries/Notificator.app/Contents/Resources/applet.rsrc
notifypy/os_notifiers/linux.py
notifypy/os_notifiers/macos.py
notifypy/os_notifiers/windows.py
notifypy/py-logo.png
notify_py-0.3.41.dist-info/METADATA
notify_py-0.3.41.dist-info/entry_points.txt
notify_py-0.3.41.dist-info/WHEEL
notify_py-0.3.41.dist-info/LICENSE
notify_py-0.3.41.dist-info/RECORD
