Metadata-Version: 2.1
Name: notify-py
Version: 0.3.41
Summary: Cross-platform desktop notification library for Python
Home-page: https://github.com/ms7m/notify-py
License: MIT
Author: Mustafa Mohamed
Author-email: mustafa@ms7m.me
Requires-Python: >=3.6,<4.0
Classifier: License :: OSI Approved :: MIT License
Classifier: Programming Language :: Python :: 3
Classifier: Programming Language :: Python :: 3.6
Classifier: Programming Language :: Python :: 3.7
Classifier: Programming Language :: Python :: 3.8
Classifier: Programming Language :: Python :: 3.9
Classifier: Programming Language :: Python :: 3.10
Classifier: Programming Language :: Python :: 3.11
Requires-Dist: jeepney ; sys_platform == "linux"
Requires-Dist: loguru (>=0.5.3,<0.6.0)
Project-URL: Documentation, https://github.com/ms7m/notify-py
Project-URL: Repository, https://github.com/ms7m/notify-py
